slack_mcp_server.py
slack_mcp_server_stateless.py
slack_mcp_server-0.2.1.dist-info/METADATA
slack_mcp_server-0.2.1.dist-info/WHEEL
slack_mcp_server-0.2.1.dist-info/entry_points.txt
slack_mcp_server-0.2.1.dist-info/top_level.txt
slack_mcp_server-0.2.1.dist-info/RECORD
