Metadata-Version: 2.4
Name: slack-mcp-server
Version: 0.2.1
Summary: A Model Context Protocol (MCP) server for Slack workspace integration using FastMCP with robust authentication and caching
Author-email: Your Name <your.email@example.com>
License-Expression: MIT
Project-URL: Homepage, https://github.com/yourusername/slack-mcp-server
Project-URL: Repository, https://github.com/yourusername/slack-mcp-server
Project-URL: Issues, https://github.com/yourusername/slack-mcp-server/issues
Keywords: slack,mcp,model-context-protocol,fastmcp,http,api,authentication,caching,workspace
Classifier: Development Status :: 4 - Beta
Classifier: Intended Audience :: Developers
Classifier: Programming Language :: Python :: 3
Classifier: Programming Language :: Python :: 3.11
Classifier: Programming Language :: Python :: 3.12
Classifier: Programming Language :: Python :: 3.13
Classifier: Topic :: Communications :: Chat
Classifier: Topic :: Software Development :: Libraries :: Python Modules
Classifier: Topic :: Internet :: WWW/HTTP :: HTTP Servers
Classifier: Operating System :: OS Independent
Requires-Python: >=3.11
Requires-Dist: fastmcp>=0.9.0
Requires-Dist: requests>=2.25.0
Requires-Dist: python-dotenv>=0.19.0
Requires-Dist: fastapi>=0.100.0
Requires-Dist: mcp>=1.1.0
Requires-Dist: starlette>=0.25.0
Requires-Dist: uvicorn>=0.20.0
Provides-Extra: dev
Requires-Dist: pytest; extra == "dev"
Requires-Dist: black; extra == "dev"
Requires-Dist: flake8; extra == "dev"
Requires-Dist: mypy; extra == "dev"
Requires-Dist: uvicorn; extra == "dev"
Requires-Dist: httpx; extra == "dev"
